arm_kernel/__init__.py
arm_kernel/__main__.py
arm_kernel/arm_kernel.py
arm_kernel/emulator.py
arm_kernel/emulator_test.py
arm_kernel/install.py
arm_kernel/kernel.json
arm_kernel/memory.py
arm_kernel/parser.py
arm_kernel/preprocessor.py
arm_kernel/registers.py
arm_kernel/view.py
arm_kernel/viewparse_exp.py
arm_kernel/templates/__init__.py
arm_kernel/templates/register_view.html
arm_kernel/templates/register_view_temps.py
arm_kernel/templates/stack_view_temp.py
arm_kernel/templates/test.html
arm_kernel-1.0.data/data/share/jupyter/kernels/arm/kernel.json
arm_kernel-1.0.dist-info/METADATA
arm_kernel-1.0.dist-info/WHEEL
arm_kernel-1.0.dist-info/licenses/LICENSE
arm_kernel-1.0.dist-info/RECORD
