Metadata-Version: 2.1
Name: arm-kernel
Version: 1.0
Summary: Jupyter kernel for ARM Assemble language.
Project-URL: Documentation, https://github.com/SamuelAl/arm_kernel#readme
Project-URL: Issues, https://github.com/SamuelAl/arm_kernel/issues
Project-URL: Source, https://github.com/SamuelAl/arm_kernel
Author-email: "Alarco Cantos, Samuel" <alarcocs@tcd.ie>
License:                     GNU GENERAL PUBLIC LICENSE
License-File: LICENSE
Keywords: ARM,assembly,jupyter,kernel
Classifier: Development Status :: 4 - Beta
Classifier: Programming Language :: Python
Classifier: Programming Language :: Python :: 3.7
Classifier: Programming Language :: Python :: 3.8
Classifier: Programming Language :: Python :: 3.9
Classifier: Programming Language :: Python :: 3.10
Classifier: Programming Language :: Python :: 3.11
Classifier: Programming Language :: Python :: Implementation :: CPython
Classifier: Programming Language :: Python :: Implementation :: PyPy
Requires-Python: >=3.7
Requires-Dist: bitstring>=4.0.1
Requires-Dist: ipykernel>=6.20.2
Requires-Dist: jinja2>=3.1.2
Requires-Dist: jupyter-client
Requires-Dist: keystone-engine>=0.9.2
Requires-Dist: pynumparser>=1.4.1
Requires-Dist: pyparsing>=3.0.9
Requires-Dist: pyyaml>=6.0
Requires-Dist: sortedcontainers>=2.4.0
Requires-Dist: unicorn
